{
  "memorial_url": "https://www.findagrave.com/memorial/128167507/gerrit-jan-vandeworp",
  "name": "Gerrit Jan “Gerry” Vandeworp",
  "birth_date": "1936-05-15",
  "death_date": "2014-04-17",
  "cemetery": "Crediton Cemetery",
  "location": "Crediton",
  "part_bio": "VANDEWORP: Gerrit (Gerry) of Exeter and formerly of the NetherlandsVANDEWORP: Gerrit (Gerry) of Exeter and formerly of the NetherlandsHomeward Bound! At Queensway Nursing Home, Hensall on Thursday, April 17, 2014 of Exeter in his 78th year.  Cherished husband, soul mate, and  life-long partner of Sandra (Finkbeiner) Vandeworp for over 50 years.  Loving and proud father of Evert Vandeworp and Lisa Brunke of Bridgman, Michigan and Rhonda Vandeworp and Samuel Tumiwa of Alexandria, Virginia.  Adoring Opa of step-grandchildren Lena Albanelli and Jessilyn Albanelli, and grandchildren Maya Tumiwa and Jayden Tumiwa.  Dear brother and brother-in-law of Bill and Elaine Vandeworp of Dashwood, Annie Vandeworp of London, Alie and Earl Forth of Wetaskiwin, Alberta, Dick and Yen Vandeworp of Mt. Brydges and Angela Vandeworp of Exeter.  Predeceased by an infant daughter Ruth Elaine, his parents Evert and Antje (Roessink) Vandeworp, brothers Albert (2011), John, and  infant brother Johannes.  Fondly remembered by very close family friend Shirley Morrow of London, his extended Canadian and Dutch family members, the Finkbeiner clan and Canadian and American friends.In April 1951, Gerry and his family immigrated from Heino, Netherlands (Gerry's much-loved homeland) to begin a new life in Ontario, Canada.  At the age of 21, Gerry attended Briercrest College and Seminary in Caronport, Saskatchewan.  Upon graduating, Gerry served as executive director of the House of Friendship in Kitchener, Ontario for 17 years.  Then, as an ordained Mennonite minister, Gerry pastored Bethel Mennonite Church, Elora, Ontario and Stoner Heights Mennonite, Louisville, Ohio until his retirement.  Gerry will be remembered for his deep love for his family, strong Christian faith, creative photography, enthusiastic antique collecting, avid vegetable and flower gardening and his infectious laughter.Many heartfelt thanks to all the staff at Hensall's Queensway Nursing Home for their care and compassion over the past four years as Gerry battled medical issues.Friends may call at the Haskett Funeral Home, 370 William Street, one west of Main, Exeter on Monday evening from 7-9 PM where the funeral service will be held on Tuesday, April 22 at 2 PM with Pastor Lester Kehl and Pastors Charleen and Kendall Jongejan Harder officiating. Interment Crediton Cemetery.Donations to the House of Friendship (Kitchener), Mennonite Central Committee of Ontario or Queensway Nursing Home – Residents' Fund would be appreciated by the family",
  "bio": "VANDEWORP: Gerrit (Gerry) of Exeter and formerly of the Netherlands<br/>VANDEWORP: Gerrit (Gerry) of Exeter and formerly of the Netherlands<br/>Homeward Bound! At Queensway Nursing Home, Hensall on Thursday, April 17, 2014 of Exeter in his 78th year.  Cherished husband, soul mate, and  life-long partner of Sandra (Finkbeiner) Vandeworp for over 50 years.  Loving and proud father of Evert Vandeworp and Lisa Brunke of Bridgman, Michigan and Rhonda Vandeworp and Samuel Tumiwa of Alexandria, Virginia.  Adoring Opa of step-grandchildren Lena Albanelli and Jessilyn Albanelli, and grandchildren Maya Tumiwa and Jayden Tumiwa.  Dear brother and brother-in-law of Bill and Elaine Vandeworp of Dashwood, Annie Vandeworp of London, Alie and Earl Forth of Wetaskiwin, Alberta, Dick and Yen Vandeworp of Mt. Brydges and Angela Vandeworp of Exeter.  Predeceased by an infant daughter Ruth Elaine, his parents Evert and Antje (Roessink) Vandeworp, brothers Albert (2011), John, and  infant brother Johannes.  Fondly remembered by very close family friend Shirley Morrow of London, his extended Canadian and Dutch family members, the Finkbeiner clan and Canadian and American friends.<br/>In April 1951, Gerry and his family immigrated from Heino, Netherlands (Gerry's much-loved homeland) to begin a new life in Ontario, Canada.  At the age of 21, Gerry attended Briercrest College and Seminary in Caronport, Saskatchewan.  Upon graduating, Gerry served as executive director of the House of Friendship in Kitchener, Ontario for 17 years.  Then, as an ordained Mennonite minister, Gerry pastored Bethel Mennonite Church, Elora, Ontario and Stoner Heights Mennonite, Louisville, Ohio until his retirement.  Gerry will be remembered for his deep love for his family, strong Christian faith, creative photography, enthusiastic antique collecting, avid vegetable and flower gardening and his infectious laughter.<br/>Many heartfelt thanks to all the staff at Hensall's Queensway Nursing Home for their care and compassion over the past four years as Gerry battled medical issues.<br/>Friends may call at the Haskett Funeral Home, 370 William Street, one west of Main, Exeter on Monday evening from 7-9 PM where the funeral service will be held on Tuesday, April 22 at 2 PM with Pastor Lester Kehl and Pastors Charleen and Kendall Jongejan Harder officiating. Interment Crediton Cemetery.<br/>Donations to the House of Friendship (Kitchener), Mennonite Central Committee of Ontario or Queensway Nursing Home – Residents' Fund would be appreciated by the family",
  "gps": null,
  "image_url": "https://images.findagrave.com/photos/2017/114/128167507_1493131634.jpg?size=photos250",
  "image_credits": "Jcarter",
  "image_credits_url": "/user/profile/48847489",
  "parents": [
    {
      "name": "Evert   Vandeworp",
      "birth_date": "1908-00-00",
      "death_date": "1959-00-00",
      "profile_url": "/memorial/18061400/evert-vandeworp"
    },
    {
      "name": "Antje  Roessink Vandeworp",
      "birth_date": "1915-00-00",
      "death_date": "1995-00-00",
      "profile_url": "/memorial/18061406/antje-vandeworp"
    }
  ],
  "spouses": [],
  "children": [],
  "siblings": "[{\"name\": \"Antje Evertina \\\"Annie\\\"  Vandeworp\", \"birth_date\": \"1943-00-00\", \"death_date\": \"1943-00-00\", \"profile_url\": \"/memorial/204752890/antje_evertina-vandeworp\"}, {\"name\": \"Aaltje Alberta \\\"Alie\\\" Van De Worp Forth\", \"birth_date\": \"1947-00-00\", \"death_date\": \"2016-00-00\", \"profile_url\": \"/memorial/158528845/aaltje_alberta-forth\"}, {\"name\": \"John William   Vandeworp\", \"birth_date\": \"1956-00-00\", \"death_date\": \"1957-00-00\", \"profile_url\": \"/memorial/18061423/john_william-vandeworp\"}]",
  "half_siblings": [],
  "plot_value": "",
  "title": "",
  "prefix": "",
  "photos": "[]",
  "maiden_name": "",
  "inscription": "",
  "id": 1088
}