{
  "memorial_url": "https://www.findagrave.com/memorial/15426274/louisa-eilber",
  "name": "Louisa Morlock Eilber",
  "birth_date": "1870-03-10",
  "death_date": "1941-11-28",
  "cemetery": "Crediton Cemetery",
  "location": "Crediton",
  "part_bio": "Daughter of Charlotte (Beaver) and Gottlieb Morlock",
  "bio": "Daughter of Charlotte (Beaver) and Gottlieb Morlock",
  "gps": {
    "latitude": "43.298789",
    "longitude": "-81.5527762"
  },
  "image_url": "https://images.findagrave.com/photos/2006/231/15426274_115607727998.jpg?size=photos250",
  "image_credits": "Scott Buschlen",
  "image_credits_url": "/user/profile/46583152",
  "parents": [],
  "spouses": [],
  "children": [],
  "siblings": [],
  "half_siblings": [],
  "plot_value": "20-1",
  "title": "",
  "prefix": "",
  "photos": "[]",
  "maiden_name": "Morlock",
  "inscription": "",
  "id": 191
}