{
  "memorial_url": "https://www.findagrave.com/memorial/16330944/rosina-finkbeiner",
  "name": "Rosina Schatz Finkbeiner",
  "birth_date": "",
  "death_date": "1882-02-03",
  "cemetery": "Crediton Cemetery",
  "location": "Crediton",
  "part_bio": "Wife of Jacob Finkbeiner",
  "bio": "FINKBEINER\nJacob Finkbeiner<br/>Gestboren Den. Marz. 12, 1861 In Alter<br/>von 11 Jahr 6 monate 2 tage.<br/>Heir Ruht<br/>Rosina<br/>Ehefrau von Jacob Finkbeiner<br/>Gestboren Dec Feb. 3, 1882 In Alter<br/>von 54 Jahr 5 tagen<br/>Ruhe uhrer a sche<br/>Jacob Finkbeiner<br/>gestboren den Apr. 8, 1900 In Alter<br/>von 79 Jahr. 6 mo. 18 tag.<br/>Magdalena<br/>wife of Christian Finkbeiner<br/>died Dec. 8, 1927<br/>aged 69 years<br/>Christian Finkbeiner<br/>died Dec. 12, 1933 aged 81 yrs.</br>",
  "gps": null,
  "image_url": "https://images.findagrave.com/photos/2006/298/16330944_116187788951.jpg?size=photos250",
  "image_credits": "Scott Buschlen",
  "image_credits_url": "/user/profile/46583152",
  "parents": [],
  "spouses": [
    {
      "name": "Jacob   Finkbeiner",
      "birth_date": "1820-00-00",
      "death_date": "1900-00-00",
      "profile_url": "/memorial/16330892/jacob-finkbeiner"
    }
  ],
  "children": "[{\"name\": \"Jacob   Finkbeiner\", \"birth_date\": \"1849-00-00\", \"death_date\": \"1861-00-00\", \"profile_url\": \"/memorial/16331140/jacob-finkbeiner\"}, {\"name\": \"Michael   Finkbeiner\", \"birth_date\": \"1856-00-00\", \"death_date\": \"1926-00-00\", \"profile_url\": \"/memorial/16671570/michael-finkbeiner\"}, {\"name\": \"Fredrick   Finkbeiner\", \"birth_date\": \"1858-00-00\", \"death_date\": \"1934-00-00\", \"profile_url\": \"/memorial/143602042/fredrick-finkbeiner\"}]",
  "siblings": "[]",
  "half_siblings": "[]",
  "plot_value": "9-3",
  "title": "",
  "prefix": "",
  "photos": "[]",
  "maiden_name": "Schatz",
  "inscription": "FINKBEINERJacob FinkbeinerGestboren Den. Marz. 12, 1861 In Altervon 11 Jahr 6 monate 2 tage.Heir RuhtRosinaEhefrau von Jacob FinkbeinerGestboren Dec Feb. 3, 1882 In Altervon 54 Jahr 5 tagenRuhe uhrer a scheJacob Finkbeinergestboren den Apr. 8, 1900 In Altervon 79 Jahr. 6 mo. 18 tag.Magdalenawife of Christian Finkbeinerdied Dec. 8, 1927aged 69 yearsChristian Finkbeinerdied Dec. 12, 1933 aged 81 yrs.",
  "id": 361
}