{
  "memorial_url": "https://www.findagrave.com/memorial/16627202/mary-e-gaiser",
  "name": "Mary E Truemner Gaiser",
  "birth_date": "1860-00-00",
  "death_date": "1936-00-00",
  "cemetery": "Crediton Cemetery",
  "location": "Crediton",
  "bio": "",
  "gps": null,
  "image_url": "https://images.findagrave.com/photos/2006/315/16627202_116339671662.jpg?size=photos250",
  "parents": [],
  "spouses": [
    {
      "name": "Jacob   Gaiser",
      "birth_date": "1854-00-00",
      "death_date": "1928-00-00",
      "profile_url": "/memorial/16627163/jacob-gaiser"
    }
  ],
  "children": "[]",
  "siblings": "[]",
  "id": 417
}