{
  "memorial_url": "https://www.findagrave.com/memorial/238052306/janet-s-bennewies",
  "name": "Janet S. Bennewies",
  "birth_date": "1950-00-00",
  "death_date": "1999-00-00",
  "cemetery": "Crediton Cemetery",
  "location": "Crediton",
  "part_bio": "",
  "bio": "BENNEWIES\nJanet S.<br/>1950-1999</br>",
  "gps": {
    "latitude": "43.2985792",
    "longitude": "-81.5527643"
  },
  "image_url": "https://images.findagrave.com/photos/2022/86/238052306_2a17caf4-673c-4592-b716-433f3005313b.jpeg?size=photos250",
  "image_credits": "patricia van horn",
  "image_credits_url": "/user/profile/49867182",
  "parents": [],
  "spouses": [],
  "children": [],
  "siblings": "[]",
  "half_siblings": [],
  "plot_value": "",
  "title": "",
  "prefix": "",
  "photos": "[]",
  "maiden_name": "",
  "inscription": "BENNEWIESJanet S.1950-1999",
  "id": 47
}