{
  "memorial_url": "https://www.findagrave.com/memorial/41011902/william-john-payne",
  "name": "William John Payne",
  "birth_date": "1934-00-00",
  "death_date": "2005-02-04",
  "cemetery": "Crediton Cemetery",
  "location": "Crediton",
  "part_bio": "PAYNE: Peacefully, at Bluewater Health, Norman Street Site, Sarnia, Friday, February 4, 2005, William John \"Bill\" Payne, 70, of Sumac Lodge, Sarnia, formerly of Crediton and Thedford. Beloved husband of the late Lois Ruth (Clarke) Payne (1996). Loved father and father-in-law of Bob Payne and Corry Elliott of Parkhill, Cheryl and Rob Dunnell of RR 2, Dashwood, Ken and Laurie Payne of Watford, Bill Payne Jr. of Crediton, Jim Payne and Shelly White of Lucan, Brian and Dawn Payne of Windsor, Tracy Payne and Dennis Evans of Thedford, Kevin and Theressa Payne of Parkhill. Loved by his many grandchildren and a great-granddaughter. Dear brother and brother-in-law of Clara and Ron Wade, Marion Payne, Lillian Joyce, Liz and Bruce Currie, Georgette and Allan Campbell, Edna and Don Clarke, Bob Payne, Sharon and Dave Medd, Shelly and Tim Sullivan. Remembered by his many nieces, nephews and their families. Predeceased by granddaughter Aimee Payne (1998), parents William and Marion (Cousins) Payne. Resting at the T. Harry Hoffman & Sons Funeral Home, Dashwood, with visitation Monday, 2 to 4 p.m. and 7 to 9 p.m.; where the funeral service will be held Tuesday, February 8, 2005 at 11 a.m. The Rev. Sheila Macgregor officiating. Interment Crediton Cemetery. If desired, memorial donations to the Alzheimer Society or charity of choice would be appreciated.",
  "bio": "PAYNE: Peacefully, at Bluewater Health, Norman Street Site, Sarnia, Friday, February 4, 2005, William John \"Bill\" Payne, 70, of Sumac Lodge, Sarnia, formerly of Crediton and Thedford. Beloved husband of the late Lois Ruth (Clarke) Payne (1996). Loved father and father-in-law of Bob Payne and Corry Elliott of Parkhill, Cheryl and Rob Dunnell of RR 2, Dashwood, Ken and Laurie Payne of Watford, Bill Payne Jr. of Crediton, Jim Payne and Shelly White of Lucan, Brian and Dawn Payne of Windsor, Tracy Payne and Dennis Evans of Thedford, Kevin and Theressa Payne of Parkhill. Loved by his many grandchildren and a great-granddaughter. Dear brother and brother-in-law of Clara and Ron Wade, Marion Payne, Lillian Joyce, Liz and Bruce Currie, Georgette and Allan Campbell, Edna and Don Clarke, Bob Payne, Sharon and Dave Medd, Shelly and Tim Sullivan. Remembered by his many nieces, nephews and their families. Predeceased by granddaughter Aimee Payne (1998), parents William and Marion (Cousins) Payne. Resting at the T. Harry Hoffman &amp; Sons Funeral Home, Dashwood, with visitation Monday, 2 to 4 p.m. and 7 to 9 p.m.; where the funeral service will be held Tuesday, February 8, 2005 at 11 a.m. The Rev. Sheila Macgregor officiating. Interment Crediton Cemetery. If desired, memorial donations to the Alzheimer Society or charity of choice would be appreciated. <br/>",
  "gps": null,
  "image_url": "https://images.findagrave.com/photos/2015/272/41011902_1443623432.jpg?size=photos250",
  "image_credits": "Peaceful1",
  "image_credits_url": "/user/profile/46601306",
  "parents": [],
  "spouses": [],
  "children": [],
  "siblings": [],
  "half_siblings": [],
  "plot_value": "",
  "title": "",
  "prefix": "",
  "photos": "[]",
  "maiden_name": "",
  "inscription": "",
  "id": 827
}