{
  "memorial_url": "https://www.findagrave.com/memorial/188136676/elodia-rita-schenk",
  "name": "Elodia Rita Cholette Schenk",
  "birth_date": "1925-00-00",
  "death_date": "1995-00-00",
  "cemetery": "Crediton Cemetery",
  "location": "Crediton",
  "part_bio": "",
  "bio": "SCHENK\nGerald Austin Schenk<br/>born 1920 died 2010<br/>his beloved wife<br/>Elodia Rita Cholette<br/>born 1925 died 1995<br/>Donald Arthur <br/>1952-1979<br/>his wife Bonnie L. Neeb<br/>loving father of Kathy, Kelly &amp; Kristian</br>",
  "gps": null,
  "image_url": "https://images.findagrave.com/photos/2018/209/188136676_cfe0b75a-00c4-4ba6-9ef8-a383b1dc4833.jpeg?size=photos250",
  "image_credits": "rossddickson",
  "image_credits_url": "/user/profile/49188008",
  "parents": [],
  "spouses": [
    {
      "name": "Gerald Austin \"Jerry\"  Schenk",
      "birth_date": "1920-00-00",
      "death_date": "2010-00-00",
      "profile_url": "/memorial/60742271/gerald_austin-schenk",
      "image_url": "https://images.findagrave.com/photos/2018/209/60742271_63b33dfc-99c9-4466-8c91-98bbc187866b.jpeg?size=photos250",
      "id": 920
    }
  ],
  "children": "[]",
  "siblings": "[]",
  "half_siblings": "[]",
  "plot_value": "Row 27-2",
  "title": "",
  "prefix": "",
  "photos": "[]",
  "maiden_name": "Cholette",
  "inscription": "SCHENKGerald Austin Schenkborn 1920 died 2010his beloved wifeElodia Rita Choletteborn 1925 died 1995Donald Arthur 1952-1979his wife Bonnie L. Neebloving father of Kathy, Kelly & Kristian",
  "id": 919
}