{
  "memorial_url": "https://www.findagrave.com/memorial/188136683/henry-g-schenk",
  "name": "Henry G. Schenk",
  "birth_date": "1887-00-00",
  "death_date": "1960-00-00",
  "cemetery": "Crediton Cemetery",
  "location": "Crediton",
  "bio": "",
  "gps": null,
  "image_url": "https://images.findagrave.com/photos/2022/84/188136683_b21e0959-e9f0-457b-bc64-b0b57a15a4ea.jpeg?size=photos250",
  "parents": [],
  "spouses": [
    {
      "name": "Pearl M.  Witmer Schenk",
      "birth_date": "1898-00-00",
      "death_date": "1951-00-00",
      "profile_url": "/memorial/188136705/pearl_m-schenk"
    }
  ],
  "children": "[]",
  "siblings": "[]",
  "id": 923
}